anondrop/__init__.py
anondrop/config.py
anondrop/main.py
anondrop-0.2.3.dist-info/licenses/LICENSE
anondrop-0.2.3.dist-info/METADATA
anondrop-0.2.3.dist-info/WHEEL
anondrop-0.2.3.dist-info/top_level.txt
anondrop-0.2.3.dist-info/RECORD
