Metadata-Version: 2.4
Name: anondrop
Version: 0.2.3
Summary: A package for uploading and deleting files using AnonDrop API
Home-page: https://github.com/BubblePlayzTHEREAL/AnonDrop
Author: BubblePlayz
Author-email: BubblePlayz <mylaptop4768@gmail.com>
License: MIT
Keywords: anondrop,upload,delete,files
Classifier: Programming Language :: Python :: 3
Classifier: License :: OSI Approved :: MIT License
Classifier: Operating System :: OS Independent
Requires-Python: >=3.6
License-File: LICENSE
Requires-Dist: requests>=2.25.1
Dynamic: author
Dynamic: home-page
Dynamic: license-file
Dynamic: requires-python
